README.rst
setup.py
lexery/__init__.py
lexery/py.typed
lexery.egg-info/PKG-INFO
lexery.egg-info/SOURCES.txt
lexery.egg-info/dependency_links.txt
lexery.egg-info/requires.txt
lexery.egg-info/top_level.txt